sonarr/__init__.py
sonarr/api_client.py
sonarr/api_response.py
sonarr/configuration.py
sonarr/exceptions.py
sonarr/py.typed
sonarr/rest.py
sonarr/api/__init__.py
sonarr/api/api_info_api.py
sonarr/api/authentication_api.py
sonarr/api/auto_tagging_api.py
sonarr/api/backup_api.py
sonarr/api/blocklist_api.py
sonarr/api/calendar_api.py
sonarr/api/calendar_feed_api.py
sonarr/api/command_api.py
sonarr/api/custom_filter_api.py
sonarr/api/custom_format_api.py
sonarr/api/cutoff_api.py
sonarr/api/delay_profile_api.py
sonarr/api/disk_space_api.py
sonarr/api/download_client_api.py
sonarr/api/download_client_config_api.py
sonarr/api/episode_api.py
sonarr/api/episode_file_api.py
sonarr/api/file_system_api.py
sonarr/api/health_api.py
sonarr/api/history_api.py
sonarr/api/host_config_api.py
sonarr/api/import_list_api.py
sonarr/api/import_list_config_api.py
sonarr/api/import_list_exclusion_api.py
sonarr/api/indexer_api.py
sonarr/api/indexer_config_api.py
sonarr/api/indexer_flag_api.py
sonarr/api/language_api.py
sonarr/api/language_profile_api.py
sonarr/api/language_profile_schema_api.py
sonarr/api/localization_api.py
sonarr/api/log_api.py
sonarr/api/log_file_api.py
sonarr/api/manual_import_api.py
sonarr/api/media_cover_api.py
sonarr/api/media_management_config_api.py
sonarr/api/metadata_api.py
sonarr/api/missing_api.py
sonarr/api/naming_config_api.py
sonarr/api/notification_api.py
sonarr/api/parse_api.py
sonarr/api/ping_api.py
sonarr/api/quality_definition_api.py
sonarr/api/quality_profile_api.py
sonarr/api/quality_profile_schema_api.py
sonarr/api/queue_action_api.py
sonarr/api/queue_api.py
sonarr/api/queue_details_api.py
sonarr/api/queue_status_api.py
sonarr/api/release_api.py
sonarr/api/release_profile_api.py
sonarr/api/release_push_api.py
sonarr/api/remote_path_mapping_api.py
sonarr/api/rename_episode_api.py
sonarr/api/root_folder_api.py
sonarr/api/season_pass_api.py
sonarr/api/series_api.py
sonarr/api/series_editor_api.py
sonarr/api/series_folder_api.py
sonarr_py-1.1.0.dist-info/METADATA
sonarr_py-1.1.0.dist-info/WHEEL
sonarr_py-1.1.0.dist-info/top_level.txt
sonarr_py-1.1.0.dist-info/RECORD
